aloe/__init__.py
aloe/codegen.py
aloe/exceptions.py
aloe/fs.py
aloe/parser.py
aloe/registry.py
aloe/strings.py
aloe/testclass.py
aloe/tools.py
aloe/utils.py
aloe/steps/__init__.py
aloe/steps/factoryboy.py
aloe_sphinx/__init__.py
aloe_sphinx/autosteps.py
aloe_sphinx/gherkindomain.py
pytest_eucalyptus/__init__.py
pytest_eucalyptus/plugin.py
tests/bad_steps_app/__init__.py
tests/bad_steps_app/features/dummy.feature
tests/bad_steps_app/features/steps/__init__.py
tests/bad_steps_app_2/__init__.py
tests/bad_steps_app_2/features/__init__.py
tests/bad_steps_app_2/features/dummy.feature
tests/bad_steps_app_2/features/steps.py
tests/callbacks_app/__init__.py
tests/callbacks_app/features/__init__.py
tests/callbacks_app/features/all_callbacks_1.feature
tests/callbacks_app/features/all_callbacks_2.feature
tests/callbacks_app/features/behave_as.feature
tests/callbacks_app/features/behave_as_ru.feature
tests/callbacks_app/features/example_callbacks.feature
tests/callbacks_app/features/feature_callbacks_1.feature
tests/callbacks_app/features/feature_callbacks_2.feature
tests/callbacks_app/features/step_callbacks.feature
tests/callbacks_app/features/step_failed.feature
tests/callbacks_app/features/steps.py
tests/callbacks_app/features/testcase_methods.feature
tests/factoryboy_app/__init__.py
tests/factoryboy_app/features/__init__.py
tests/factoryboy_app/features/bad.feature
tests/factoryboy_app/features/good.feature
tests/factoryboy_app/features/steps.py
tests/functional/__init__.py
tests/functional/test_callbacks.py
tests/functional/test_factoryboy.py
tests/functional/test_simple.py
tests/simple_app/__init__.py
tests/simple_app/features/__init__.py
tests/simple_app/features/background.feature
tests/simple_app/features/calculator.feature
tests/simple_app/features/calculator_zh.feature
tests/simple_app/features/exact_match.feature
tests/simple_app/features/highlighting.feature
tests/simple_app/features/outlines.feature
tests/simple_app/features/scenario_index.feature
pytest_eucalyptus-0.4.1.dist-info/LICENSE
pytest_eucalyptus-0.4.1.dist-info/METADATA
pytest_eucalyptus-0.4.1.dist-info/WHEEL
pytest_eucalyptus-0.4.1.dist-info/entry_points.txt
pytest_eucalyptus-0.4.1.dist-info/top_level.txt
pytest_eucalyptus-0.4.1.dist-info/RECORD
