Metadata-Version: 2.1
Name: pytest-eucalyptus
Version: 0.4.1
Summary: Pytest Plugin for BDD
Home-page: https://github.com/wayfair/pytest-eucalyptus
Author: Dennis Miasoutov
Author-email: dmiasoutov@wayfair.com
Classifier: License :: OSI Approved :: Apache Software License
Classifier: Programming Language :: Python
Classifier: Programming Language :: Python :: 3
Classifier: Framework :: Pytest
License-File: LICENSE
Requires-Dist: ansicolors (>=1.1.8)
Requires-Dist: colorama (>=0.3.9)
Requires-Dist: gherkin-official (<5,>=4.1.3)
Requires-Dist: repoze.lru
Requires-Dist: pytest (>=4.2.0)
Provides-Extra: tests_require
Requires-Dist: coverage ; extra == 'tests_require'
Requires-Dist: factory-boy ; extra == 'tests_require'
Requires-Dist: mock ; extra == 'tests_require'
Requires-Dist: pycodestyle ; extra == 'tests_require'
Requires-Dist: pylint (>=2.4.3) ; extra == 'tests_require'
Requires-Dist: setuptools-scm ; extra == 'tests_require'
Requires-Dist: Sphinx (>=2.1.2) ; extra == 'tests_require'
Requires-Dist: pytest-cov (==2.5.1) ; extra == 'tests_require'
